Crypto/Crypto.py
Crypto/__init__.py
lgjs_crypto_v2-0.1.dist-info/METADATA
lgjs_crypto_v2-0.1.dist-info/WHEEL
lgjs_crypto_v2-0.1.dist-info/top_level.txt
lgjs_crypto_v2-0.1.dist-info/RECORD
